llama_index/packs/self_rag/__init__.py
llama_index/packs/self_rag/base.py
llama_index_packs_self_rag-0.4.1.dist-info/METADATA
llama_index_packs_self_rag-0.4.1.dist-info/WHEEL
llama_index_packs_self_rag-0.4.1.dist-info/licenses/LICENSE
llama_index_packs_self_rag-0.4.1.dist-info/RECORD
