Metadata-Version: 2.4
Name: llama-index-packs-self-rag
Version: 0.4.1
Summary: llama-index packs self rag integration
Author-email: Your Name <you@example.com>
Maintainer: mmaatouk
License-Expression: MIT
License-File: LICENSE
Keywords: llm,self-RAG,smart-retreiver
Requires-Python: <4.0,>=3.9
Requires-Dist: llama-cpp-python<0.3,>=0.2.39
Requires-Dist: llama-index-core<0.15,>=0.13.0
